mmrotate/__init__.py
mmrotate/registry.py
mmrotate/version.py
mmrotate/.mim/model-index.yml
mmrotate/.mim/configs/_base_/default_runtime.py
mmrotate/.mim/configs/_base_/datasets/dior.py
mmrotate/.mim/configs/_base_/datasets/dota.py
mmrotate/.mim/configs/_base_/datasets/dota_coco.py
mmrotate/.mim/configs/_base_/datasets/dota_ms.py
mmrotate/.mim/configs/_base_/datasets/dota_qbox.py
mmrotate/.mim/configs/_base_/datasets/dotav15.py
mmrotate/.mim/configs/_base_/datasets/dotav2.py
mmrotate/.mim/configs/_base_/datasets/hrsc.py
mmrotate/.mim/configs/_base_/datasets/hrsid.py
mmrotate/.mim/configs/_base_/datasets/rsdd.py
mmrotate/.mim/configs/_base_/datasets/srsdd.py
mmrotate/.mim/configs/_base_/datasets/ssdd.py
mmrotate/.mim/configs/_base_/schedules/schedule_1x.py
mmrotate/.mim/configs/_base_/schedules/schedule_3x.py
mmrotate/.mim/configs/_base_/schedules/schedule_40e.py
mmrotate/.mim/configs/_base_/schedules/schedule_6x.py
mmrotate/.mim/configs/cfa/cfa-qbox_r50_fpn_1x_dota.py
mmrotate/.mim/configs/cfa/cfa-qbox_r50_fpn_40e_dota.py
mmrotate/.mim/configs/cfa/metafile.yml
mmrotate/.mim/configs/convnext/metafile.yml
mmrotate/.mim/configs/convnext/rotated-retinanet-rbox-le90_convnext-tiny_fpn_kld-stable_adamw-1x_dota.py
mmrotate/.mim/configs/csl/metafile.yml
mmrotate/.mim/configs/csl/rotated-retinanet-rbox-le90_r50_fpn_csl-gaussian_amp-1x_dota.py
mmrotate/.mim/configs/gliding_vertex/gliding-vertex-qbox_r50_fpn_1x_dota.py
mmrotate/.mim/configs/gliding_vertex/gliding-vertex-rbox_r50_fpn_1x_dota.py
mmrotate/.mim/configs/gliding_vertex/metafile.yml
mmrotate/.mim/configs/gwd/metafile.yml
mmrotate/.mim/configs/gwd/rotated-retinanet-hbox-oc_r50_fpn_gwd_1x_dota.py
mmrotate/.mim/configs/gwd/rotated-retinanet-rbox-le135_r50_fpn_gwd_1x_dota.py
mmrotate/.mim/configs/gwd/rotated-retinanet-rbox-le90_r50_fpn_gwd_1x_dota.py
mmrotate/.mim/configs/h2rbox/h2rbox-le90_r50_fpn_adamw-1x_dota-ms.py
mmrotate/.mim/configs/h2rbox/h2rbox-le90_r50_fpn_adamw-1x_dota.py
mmrotate_dev-1.0.1.dist-info/LICENSE
mmrotate_dev-1.0.1.dist-info/METADATA
mmrotate_dev-1.0.1.dist-info/WHEEL
mmrotate_dev-1.0.1.dist-info/top_level.txt
mmrotate_dev-1.0.1.dist-info/RECORD
